rulebricks/.DS_Store
rulebricks/__init__.py
rulebricks/assets/__init__.py
rulebricks/assets/client.py
rulebricks/assets/flows/__init__.py
rulebricks/assets/flows/client.py
rulebricks/assets/flows/raw_client.py
rulebricks/assets/folders/__init__.py
rulebricks/assets/folders/client.py
rulebricks/assets/folders/raw_client.py
rulebricks/assets/raw_client.py
rulebricks/assets/rules/__init__.py
rulebricks/assets/rules/client.py
rulebricks/assets/rules/raw_client.py
rulebricks/assets/types/__init__.py
rulebricks/assets/types/export_manifest_request_root_type.py
rulebricks/assets/types/export_rbm_assets_response.py
rulebricks/assets/types/import_manifest_request_conflict_strategy.py
rulebricks/assets/types/import_manifest_request_legacy_rule_mapping_value.py
rulebricks/assets/types/import_manifest_request_legacy_rule_mapping_value_action.py
rulebricks/assets/types/import_manifest_request_manifest.py
rulebricks/client.py
rulebricks/contexts/__init__.py
rulebricks/contexts/client.py
rulebricks/contexts/objects/__init__.py
rulebricks/contexts/objects/client.py
rulebricks/contexts/objects/raw_client.py
rulebricks/contexts/objects/types/__init__.py
rulebricks/contexts/objects/types/create_context_request_on_schema_mismatch.py
rulebricks/contexts/objects/types/create_context_request_schema_item.py
rulebricks/contexts/objects/types/update_context_request_on_schema_mismatch.py
rulebricks/contexts/objects/types/update_context_request_schema_item.py
rulebricks/contexts/raw_client.py
rulebricks/contexts/relationships/__init__.py
rulebricks/contexts/relationships/client.py
rulebricks/contexts/relationships/raw_client.py
rulebricks/contexts/relationships/types/__init__.py
rulebricks/contexts/relationships/types/create_relationship_request_relation_type.py
rulebricks/core/__init__.py
rulebricks/core/api_error.py
rulebricks/core/client_wrapper.py
rulebricks/core/datetime_utils.py
rulebricks/core/file.py
rulebricks/core/force_multipart.py
rulebricks/core/http_client.py
rulebricks-2.5.0.dist-info/LICENSE.txt
rulebricks-2.5.0.dist-info/METADATA
rulebricks-2.5.0.dist-info/WHEEL
rulebricks-2.5.0.dist-info/RECORD
