Metadata-Version: 2.1
Name: rulebricks
Version: 2.5.0
Summary: A JSON-based, server-side rule engine with a customizable decision table UI for non-technical end users
Author: Sid Garimella
Author-email: sid@rulebricks.com
Requires-Python: >=3.8,<4.0
Classifier: Programming Language :: Python :: 3
Classifier: Programming Language :: Python :: 3.8
Classifier: Programming Language :: Python :: 3.9
Classifier: Programming Language :: Python :: 3.10
Classifier: Programming Language :: Python :: 3.11
Requires-Dist: httpx (>=0.21.2)
Requires-Dist: pydantic (>=1.9.2)
Requires-Dist: tabulate (>=0.8.9,<0.9.0)
Requires-Dist: types-tabulate (>=0.8.9,<0.9.0)
Requires-Dist: typing_extensions (>=4.0.0)
